getConfig/__init__.py
getConfig/example.py
getConfig/getConfig.py
getConfig-0.0.3.dist-info/LICENSE
getConfig-0.0.3.dist-info/METADATA
getConfig-0.0.3.dist-info/WHEEL
getConfig-0.0.3.dist-info/top_level.txt
getConfig-0.0.3.dist-info/RECORD
