Metadata-Version: 2.1
Name: getConfig
Version: 0.0.3
Summary: Python module for reading variables from configuration files like cfg, INI, XML, JSON.
Home-page: https://github.com/AlexMartin17/getConfig
Author: AlexMartin17
Author-email: amkl17mz@gmail.com
License: UNKNOWN
Platform: UNKNOWN
Classifier: Programming Language :: Python :: 3
Classifier: License :: OSI Approved :: MIT License
Classifier: Operating System :: OS Independent
Requires-Python: >=3.6
